{
  "job": {
    "id": "angel",
    "jobId": 7,
    "label": "追放天使",
    "source": "angel_n_skill2020.html",
    "awake": false
  },
  "skills": [
    {
      "id": 125,
      "name": "テレキネシス",
      "icon": "https://sokomin.github.io/skill/design/image/skill/iconSkill_0125.png",
      "difficulty": 1,
      "prerequisites": "なし",
      "description": "念動力で敵を攻撃する。",
      "powerup": "威力, 速度, 麻痺確率",
      "magicAttr": null,
      "hasPhysDmgPct": true,
      "hasMagicDmgRange": false,
      "hasAttackCount": false,
      "hasActivationRate": false,
      "levelKeys": [
        1,
        2,
        3,
        4,
        5,
        6,
        7,
        8,
        9,
        10,
        20,
        30,
        40,
        50
      ],
      "levels": {
        "1": {
          "consumeCp": 0,
          "gainCp": 0.6,
          "physDmgPct": 2.5,
          "attackSpeed": 0.4
        },
        "2": {
          "consumeCp": 0,
          "gainCp": 0.7,
          "physDmgPct": 3,
          "attackSpeed": 0.8
        },
        "3": {
          "consumeCp": 0,
          "gainCp": 0.8,
          "physDmgPct": 3.5,
          "attackSpeed": 1.2
        },
        "4": {
          "consumeCp": 0,
          "gainCp": 0.9,
          "physDmgPct": 4,
          "attackSpeed": 1.6
        },
        "5": {
          "consumeCp": 0,
          "gainCp": 1,
          "physDmgPct": 4.5,
          "attackSpeed": 2
        },
        "6": {
          "consumeCp": 0,
          "gainCp": 1.1,
          "physDmgPct": 5,
          "attackSpeed": 2.4
        },
        "7": {
          "consumeCp": 0,
          "gainCp": 1.2,
          "physDmgPct": 5.5,
          "attackSpeed": 2.8
        },
        "8": {
          "consumeCp": 0,
          "gainCp": 1.3,
          "physDmgPct": 6,
          "attackSpeed": 3.2
        },
        "9": {
          "consumeCp": 0,
          "gainCp": 1.4,
          "physDmgPct": 6.5,
          "attackSpeed": 3.6
        },
        "10": {
          "consumeCp": 0,
          "gainCp": 1.5,
          "physDmgPct": 7,
          "attackSpeed": 4
        },
        "20": {
          "consumeCp": 0,
          "gainCp": 2.5,
          "physDmgPct": 12,
          "attackSpeed": 8
        },
        "30": {
          "consumeCp": 0,
          "gainCp": 3.5,
          "physDmgPct": 17,
          "attackSpeed": 12
        },
        "40": {
          "consumeCp": 0,
          "gainCp": 4.5,
          "physDmgPct": 22,
          "attackSpeed": 16
        },
        "50": {
          "consumeCp": 0,
          "gainCp": 5.5,
          "physDmgPct": 27,
          "attackSpeed": 20
        }
      }
    },
    {
      "id": 126,
      "name": "ブレスドハンマー",
      "icon": "https://sokomin.github.io/skill/design/image/skill/iconSkill_0126.png",
      "difficulty": 1,
      "prerequisites": "テレキネシス[3]",
      "description": "聖霊の祝福を受けた魔法のハンマーを召喚して敵に投げる。 攻撃された敵は光抵抗力が低下する。",
      "powerup": "威力、命中率、光抵抗力減少率",
      "magicAttr": null,
      "hasPhysDmgPct": true,
      "hasMagicDmgRange": false,
      "hasAttackCount": false,
      "hasActivationRate": false,
      "levelKeys": [
        1,
        2,
        3,
        4,
        5,
        6,
        7,
        8,
        9,
        10,
        20,
        30,
        40,
        50
      ],
      "levels": {
        "1": {
          "consumeCp": 3.3,
          "gainCp": 0.6,
          "physDmgPct": 3
        },
        "2": {
          "consumeCp": 3.6,
          "gainCp": 1.2,
          "physDmgPct": 5
        },
        "3": {
          "consumeCp": 3.9,
          "gainCp": 1.8,
          "physDmgPct": 8
        },
        "4": {
          "consumeCp": 4.2,
          "gainCp": 2.4,
          "physDmgPct": 10
        },
        "5": {
          "consumeCp": 4.5,
          "gainCp": 3,
          "physDmgPct": 13
        },
        "6": {
          "consumeCp": 4.8,
          "gainCp": 3.6,
          "physDmgPct": 15
        },
        "7": {
          "consumeCp": 5.1,
          "gainCp": 4.2,
          "physDmgPct": 18
        },
        "8": {
          "consumeCp": 5.4,
          "gainCp": 4.8,
          "physDmgPct": 20
        },
        "9": {
          "consumeCp": 5.7,
          "gainCp": 5.4,
          "physDmgPct": 23
        },
        "10": {
          "consumeCp": 6,
          "gainCp": 6,
          "physDmgPct": 25
        },
        "20": {
          "consumeCp": 9,
          "gainCp": 12,
          "physDmgPct": 50
        },
        "30": {
          "consumeCp": 12,
          "gainCp": 18,
          "physDmgPct": 75
        },
        "40": {
          "consumeCp": 15,
          "gainCp": 24,
          "physDmgPct": 100
        },
        "50": {
          "consumeCp": 18,
          "gainCp": 30,
          "physDmgPct": 125
        }
      }
    },
    {
      "id": 127,
      "name": "ヘブンリープレシング",
      "icon": "https://sokomin.github.io/skill/design/image/skill/iconSkill_0127.png",
      "difficulty": 2,
      "prerequisites": "ブレスドハンマー[6]",
      "description": "巨大な天上界のハンマーを召喚して、敵の頭上に落とす。 敵はハンマーの衝撃でしばらくレベルが低下される。",
      "powerup": "",
      "magicAttr": null,
      "hasPhysDmgPct": true,
      "hasMagicDmgRange": false,
      "hasAttackCount": true,
      "hasActivationRate": false,
      "levelKeys": [
        1,
        2,
        3,
        4,
        5,
        6,
        7,
        8,
        9,
        10,
        20,
        30,
        40,
        50
      ],
      "levels": {
        "1": {
          "consumeCp": 13.2,
          "gainCp": 3.8,
          "physDmgPct": 14,
          "attackCount": "4回"
        },
        "2": {
          "consumeCp": 14.4,
          "gainCp": 5.6,
          "physDmgPct": 18,
          "attackCount": "4回"
        },
        "3": {
          "consumeCp": 15.6,
          "gainCp": 7.4,
          "physDmgPct": 22,
          "attackCount": "4回"
        },
        "4": {
          "consumeCp": 16.8,
          "gainCp": 9.2,
          "physDmgPct": 26,
          "attackCount": "4回"
        },
        "5": {
          "consumeCp": 18,
          "gainCp": 11,
          "physDmgPct": 30,
          "attackCount": "4回"
        },
        "6": {
          "consumeCp": 19.2,
          "gainCp": 12.8,
          "physDmgPct": 34,
          "attackCount": "4回"
        },
        "7": {
          "consumeCp": 20.4,
          "gainCp": 14.6,
          "physDmgPct": 38,
          "attackCount": "4回"
        },
        "8": {
          "consumeCp": 21.6,
          "gainCp": 16.4,
          "physDmgPct": 42,
          "attackCount": "4回"
        },
        "9": {
          "consumeCp": 22.8,
          "gainCp": 18.2,
          "physDmgPct": 46,
          "attackCount": "4回"
        },
        "10": {
          "consumeCp": 24,
          "gainCp": 20,
          "physDmgPct": 50,
          "attackCount": "4回"
        },
        "20": {
          "consumeCp": 36,
          "gainCp": 38,
          "physDmgPct": 90,
          "attackCount": "4回"
        },
        "30": {
          "consumeCp": 48,
          "gainCp": 56,
          "physDmgPct": 130,
          "attackCount": "4回"
        },
        "40": {
          "consumeCp": 60,
          "gainCp": 74,
          "physDmgPct": 170,
          "attackCount": "4回"
        },
        "50": {
          "consumeCp": 72,
          "gainCp": 92,
          "physDmgPct": 210,
          "attackCount": "4回"
        }
      }
    },
    {
      "id": 128,
      "name": "フェザーニードル",
      "icon": "https://sokomin.github.io/skill/design/image/skill/iconSkill_0128.png",
      "difficulty": 2,
      "prerequisites": "テレキネシス[6]",
      "description": "聖なる力が込められた翼の羽を飛ばして攻撃する。 攻撃された敵は命中率と回避率が低下する。",
      "powerup": "威力、命中率、持続時間",
      "magicAttr": "light",
      "hasPhysDmgPct": true,
      "hasMagicDmgRange": true,
      "hasAttackCount": false,
      "hasActivationRate": false,
      "levelKeys": [
        1,
        2,
        3,
        4,
        5,
        6,
        7,
        8,
        9,
        10,
        20,
        30,
        40,
        50
      ],
      "levels": {
        "1": {
          "consumeCp": 6,
          "gainCp": 7.3,
          "physDmgPct": 3,
          "magicDmgMin": 1,
          "magicDmgMax": 3
        },
        "2": {
          "consumeCp": 7,
          "gainCp": 8.6,
          "physDmgPct": 6,
          "magicDmgMin": 2,
          "magicDmgMax": 4
        },
        "3": {
          "consumeCp": 8,
          "gainCp": 9.9,
          "physDmgPct": 9,
          "magicDmgMin": 2,
          "magicDmgMax": 4
        },
        "4": {
          "consumeCp": 9,
          "gainCp": 11.2,
          "physDmgPct": 12,
          "magicDmgMin": 2,
          "magicDmgMax": 4
        },
        "5": {
          "consumeCp": 10,
          "gainCp": 12.5,
          "physDmgPct": 15,
          "magicDmgMin": 3,
          "magicDmgMax": 5
        },
        "6": {
          "consumeCp": 11,
          "gainCp": 13.8,
          "physDmgPct": 18,
          "magicDmgMin": 3,
          "magicDmgMax": 5
        },
        "7": {
          "consumeCp": 12,
          "gainCp": 15.1,
          "physDmgPct": 21,
          "magicDmgMin": 3,
          "magicDmgMax": 5
        },
        "8": {
          "consumeCp": 13,
          "gainCp": 16.4,
          "physDmgPct": 24,
          "magicDmgMin": 3,
          "magicDmgMax": 5
        },
        "9": {
          "consumeCp": 14,
          "gainCp": 17.7,
          "physDmgPct": 27,
          "magicDmgMin": 4,
          "magicDmgMax": 6
        },
        "10": {
          "consumeCp": 15,
          "gainCp": 19,
          "physDmgPct": 30,
          "magicDmgMin": 4,
          "magicDmgMax": 6
        },
        "20": {
          "consumeCp": 25,
          "gainCp": 32,
          "physDmgPct": 60,
          "magicDmgMin": 7,
          "magicDmgMax": 9
        },
        "30": {
          "consumeCp": 35,
          "gainCp": 45,
          "physDmgPct": 90,
          "magicDmgMin": 10,
          "magicDmgMax": 12
        },
        "40": {
          "consumeCp": 45,
          "gainCp": 58,
          "physDmgPct": 120,
          "magicDmgMin": 13,
          "magicDmgMax": 15
        },
        "50": {
          "consumeCp": 55,
          "gainCp": 71,
          "physDmgPct": 150,
          "magicDmgMin": 16,
          "magicDmgMax": 18
        }
      }
    },
    {
      "id": 129,
      "name": "ホーリーサークル",
      "icon": "https://sokomin.github.io/skill/design/image/skill/iconSkill_0129.png",
      "difficulty": 3,
      "prerequisites": "フェザーニードル[6] ヘブンリープレシング[6]",
      "description": "聖霊の力が宿ったサークルを飛ばして攻撃する。 攻撃された敵は命中率と回避率が低下する。",
      "powerup": "威力、速度、持続時間",
      "magicAttr": "light",
      "hasPhysDmgPct": false,
      "hasMagicDmgRange": true,
      "hasAttackCount": false,
      "hasActivationRate": false,
      "levelKeys": [
        1,
        2,
        3,
        4,
        5,
        6,
        7,
        8,
        9,
        10,
        20,
        30,
        40,
        50
      ],
      "levels": {
        "1": {
          "consumeCp": 32.5,
          "gainCp": 3,
          "magicDmgMin": 22,
          "magicDmgMax": 25,
          "attackSpeed": 0.6
        },
        "2": {
          "consumeCp": 35,
          "gainCp": 6,
          "magicDmgMin": 24,
          "magicDmgMax": 30,
          "attackSpeed": 1.2
        },
        "3": {
          "consumeCp": 37.5,
          "gainCp": 9,
          "magicDmgMin": 26,
          "magicDmgMax": 35,
          "attackSpeed": 1.8
        },
        "4": {
          "consumeCp": 40,
          "gainCp": 12,
          "magicDmgMin": 28,
          "magicDmgMax": 40,
          "attackSpeed": 2.4
        },
        "5": {
          "consumeCp": 42.5,
          "gainCp": 15,
          "magicDmgMin": 30,
          "magicDmgMax": 45,
          "attackSpeed": 3
        },
        "6": {
          "consumeCp": 45,
          "gainCp": 18,
          "magicDmgMin": 32,
          "magicDmgMax": 50,
          "attackSpeed": 3.6
        },
        "7": {
          "consumeCp": 47.5,
          "gainCp": 21,
          "magicDmgMin": 34,
          "magicDmgMax": 55,
          "attackSpeed": 4.2
        },
        "8": {
          "consumeCp": 50,
          "gainCp": 24,
          "magicDmgMin": 36,
          "magicDmgMax": 60,
          "attackSpeed": 4.8
        },
        "9": {
          "consumeCp": 52.5,
          "gainCp": 27,
          "magicDmgMin": 38,
          "magicDmgMax": 65,
          "attackSpeed": 5.4
        },
        "10": {
          "consumeCp": 55,
          "gainCp": 30,
          "magicDmgMin": 40,
          "magicDmgMax": 70,
          "attackSpeed": 6
        },
        "20": {
          "consumeCp": 80,
          "gainCp": 60,
          "magicDmgMin": 60,
          "magicDmgMax": 120,
          "attackSpeed": 12
        },
        "30": {
          "consumeCp": 105,
          "gainCp": 90,
          "magicDmgMin": 80,
          "magicDmgMax": 170,
          "attackSpeed": 18
        },
        "40": {
          "consumeCp": 130,
          "gainCp": 120,
          "magicDmgMin": 100,
          "magicDmgMax": 220,
          "attackSpeed": 24
        },
        "50": {
          "consumeCp": 155,
          "gainCp": 150,
          "magicDmgMin": 120,
          "magicDmgMax": 270,
          "attackSpeed": 30
        }
      }
    },
    {
      "id": 130,
      "name": "ブラッディウィング",
      "icon": "https://sokomin.github.io/skill/design/image/skill/iconSkill_0130.png",
      "difficulty": 4,
      "prerequisites": "フェザーニードル[12] ホーリーサークル[6]",
      "description": "自分の生命力を犠牲にしながら折れた翼から出る膏血を敵に撤いて攻撃する。",
      "powerup": "威力、速度、持続時間",
      "magicAttr": "light",
      "hasPhysDmgPct": false,
      "hasMagicDmgRange": true,
      "hasAttackCount": true,
      "hasActivationRate": false,
      "levelKeys": [
        1,
        2,
        3,
        4,
        5,
        6,
        7,
        8,
        9,
        10,
        20,
        30,
        40,
        50
      ],
      "levels": {
        "1": {
          "consumeCp": 68.5,
          "gainCp": 3,
          "magicDmgMin": 13,
          "magicDmgMax": 17,
          "attackSpeed": 0.3,
          "attackCount": 5
        },
        "2": {
          "consumeCp": 72,
          "gainCp": 6,
          "magicDmgMin": 14,
          "magicDmgMax": 20.5,
          "attackSpeed": 0.6,
          "attackCount": 5
        },
        "3": {
          "consumeCp": 75.5,
          "gainCp": 9,
          "magicDmgMin": 15,
          "magicDmgMax": 24,
          "attackSpeed": 0.9,
          "attackCount": 5
        },
        "4": {
          "consumeCp": 79,
          "gainCp": 12,
          "magicDmgMin": 16,
          "magicDmgMax": 27.5,
          "attackSpeed": 1.2,
          "attackCount": 5
        },
        "5": {
          "consumeCp": 82.5,
          "gainCp": 15,
          "magicDmgMin": 17,
          "magicDmgMax": 31,
          "attackSpeed": 1.5,
          "attackCount": 5
        },
        "6": {
          "consumeCp": 86,
          "gainCp": 18,
          "magicDmgMin": 18,
          "magicDmgMax": 34.5,
          "attackSpeed": 1.8,
          "attackCount": 5
        },
        "7": {
          "consumeCp": 89.5,
          "gainCp": 21,
          "magicDmgMin": 19,
          "magicDmgMax": 38,
          "attackSpeed": 2.1,
          "attackCount": 5
        },
        "8": {
          "consumeCp": 93,
          "gainCp": 24,
          "magicDmgMin": 20,
          "magicDmgMax": 41.5,
          "attackSpeed": 2.4,
          "attackCount": 5
        },
        "9": {
          "consumeCp": 96.5,
          "gainCp": 27,
          "magicDmgMin": 21,
          "magicDmgMax": 45,
          "attackSpeed": 2.7,
          "attackCount": 5
        },
        "10": {
          "consumeCp": 100,
          "gainCp": 30,
          "magicDmgMin": 22,
          "magicDmgMax": 48.5,
          "attackSpeed": 3,
          "attackCount": 5
        },
        "20": {
          "consumeCp": 135,
          "gainCp": 60,
          "magicDmgMin": 23,
          "magicDmgMax": 83.5,
          "attackSpeed": 6,
          "attackCount": 5
        },
        "30": {
          "consumeCp": 170,
          "gainCp": 90,
          "magicDmgMin": 24,
          "magicDmgMax": 118.5,
          "attackSpeed": 9,
          "attackCount": 5
        },
        "40": {
          "consumeCp": 205,
          "gainCp": 120,
          "magicDmgMin": 25,
          "magicDmgMax": 153.5,
          "attackSpeed": 12,
          "attackCount": 5
        },
        "50": {
          "consumeCp": 240,
          "gainCp": 150,
          "magicDmgMin": 26,
          "magicDmgMax": 188.5,
          "attackSpeed": 15,
          "attackCount": 5
        }
      }
    },
    {
      "id": 131,
      "name": "ホールドパーソン",
      "icon": "https://sokomin.github.io/skill/design/image/skill/iconSkill_0131.png",
      "difficulty": 1,
      "prerequisites": "ヒーリング[3]",
      "description": "人間系、悪魔系の敵の動きを封じる。",
      "powerup": "成功確率, 持続時間",
      "magicAttr": null,
      "hasPhysDmgPct": false,
      "hasMagicDmgRange": false,
      "hasAttackCount": false,
      "hasActivationRate": false,
      "levelKeys": [
        1,
        2,
        3,
        4,
        5,
        6,
        7,
        8,
        9,
        10,
        20,
        30,
        40,
        50
      ],
      "levels": {
        "1": {
          "consumeCp": 5.5,
          "gainCp": 0,
          "range": "7m"
        },
        "2": {
          "consumeCp": 6,
          "gainCp": 0,
          "range": "7m"
        },
        "3": {
          "consumeCp": 6.5,
          "gainCp": 0,
          "range": "7m"
        },
        "4": {
          "consumeCp": 7,
          "gainCp": 0,
          "range": "7m"
        },
        "5": {
          "consumeCp": 7.5,
          "gainCp": 0,
          "range": "7m"
        },
        "6": {
          "consumeCp": 8,
          "gainCp": 0,
          "range": "7m"
        },
        "7": {
          "consumeCp": 8.5,
          "gainCp": 0,
          "range": "7m"
        },
        "8": {
          "consumeCp": 9,
          "gainCp": 0,
          "range": "7m"
        },
        "9": {
          "consumeCp": 9.5,
          "gainCp": 0,
          "range": "7m"
        },
        "10": {
          "consumeCp": 10,
          "gainCp": 0,
          "range": "7m"
        },
        "20": {
          "consumeCp": 15,
          "gainCp": 0,
          "range": "7m"
        },
        "30": {
          "consumeCp": 20,
          "gainCp": 0,
          "range": "7m"
        },
        "40": {
          "consumeCp": 25,
          "gainCp": 0,
          "range": "7m"
        },
        "50": {
          "consumeCp": 30,
          "gainCp": 0,
          "range": "7m"
        }
      }
    },
    {
      "id": 132,
      "name": "ヒーリング",
      "icon": "https://sokomin.github.io/skill/design/image/skill/iconSkill_0132.png",
      "difficulty": 2,
      "prerequisites": "ホールドパーソン[6] 回想[6]",
      "description": "味方の体力を回復する。 知識値によって回復量が増加する。",
      "powerup": "回復量",
      "magicAttr": null,
      "hasPhysDmgPct": false,
      "hasMagicDmgRange": false,
      "hasAttackCount": false,
      "hasActivationRate": false,
      "levelKeys": [
        1,
        2,
        3,
        4,
        5,
        6,
        7,
        8,
        9,
        10,
        20,
        30,
        40,
        50
      ],
      "levels": {
        "1": {
          "consumeCp": 7.5,
          "gainCp": 0,
          "range": "7m"
        },
        "2": {
          "consumeCp": 10,
          "gainCp": 0,
          "range": "7m"
        },
        "3": {
          "consumeCp": 12.5,
          "gainCp": 0,
          "range": "7m"
        },
        "4": {
          "consumeCp": 15,
          "gainCp": 0,
          "range": "7m"
        },
        "5": {
          "consumeCp": 17.5,
          "gainCp": 0,
          "range": "7m"
        },
        "6": {
          "consumeCp": 20,
          "gainCp": 0,
          "range": "7m"
        },
        "7": {
          "consumeCp": 22.5,
          "gainCp": 0,
          "range": "7m"
        },
        "8": {
          "consumeCp": 25,
          "gainCp": 0,
          "range": "7m"
        },
        "9": {
          "consumeCp": 27.5,
          "gainCp": 0,
          "range": "7m"
        },
        "10": {
          "consumeCp": 30,
          "gainCp": 0,
          "range": "7m"
        },
        "20": {
          "consumeCp": 55,
          "gainCp": 0,
          "range": "7m"
        },
        "30": {
          "consumeCp": 80,
          "gainCp": 0,
          "range": "7m"
        },
        "40": {
          "consumeCp": 105,
          "gainCp": 0,
          "range": "7m"
        },
        "50": {
          "consumeCp": 130,
          "gainCp": 0,
          "range": "7m"
        }
      }
    },
    {
      "id": 133,
      "name": "ホールドモンスター",
      "icon": "https://sokomin.github.io/skill/design/image/skill/iconSkill_0133.png",
      "difficulty": 2,
      "prerequisites": "ホールドパーソン[6] テレキネシス[6]",
      "description": "動物系、神獣系の敵の動きを封じる。",
      "powerup": "成功確率, 持続時間",
      "magicAttr": null,
      "hasPhysDmgPct": false,
      "hasMagicDmgRange": false,
      "hasAttackCount": false,
      "hasActivationRate": false,
      "levelKeys": [
        1,
        2,
        3,
        4,
        5,
        6,
        7,
        8,
        9,
        10,
        20,
        30,
        40,
        50
      ],
      "levels": {
        "1": {
          "consumeCp": 10.5,
          "gainCp": 0,
          "range": "7m"
        },
        "2": {
          "consumeCp": 11,
          "gainCp": 0,
          "range": "7m"
        },
        "3": {
          "consumeCp": 11.5,
          "gainCp": 0,
          "range": "7m"
        },
        "4": {
          "consumeCp": 12,
          "gainCp": 0,
          "range": "7m"
        },
        "5": {
          "consumeCp": 12.5,
          "gainCp": 0,
          "range": "7m"
        },
        "6": {
          "consumeCp": 13,
          "gainCp": 0,
          "range": "7m"
        },
        "7": {
          "consumeCp": 13.5,
          "gainCp": 0,
          "range": "7m"
        },
        "8": {
          "consumeCp": 14,
          "gainCp": 0,
          "range": "7m"
        },
        "9": {
          "consumeCp": 14.5,
          "gainCp": 0,
          "range": "7m"
        },
        "10": {
          "consumeCp": 15,
          "gainCp": 0,
          "range": "7m"
        },
        "20": {
          "consumeCp": 20,
          "gainCp": 0,
          "range": "7m"
        },
        "30": {
          "consumeCp": 25,
          "gainCp": 0,
          "range": "7m"
        },
        "40": {
          "consumeCp": 30,
          "gainCp": 0,
          "range": "7m"
        },
        "50": {
          "consumeCp": 35,
          "gainCp": 0,
          "range": "7m"
        }
      }
    },
    {
      "id": 134,
      "name": "マジックディスペリング",
      "icon": "https://sokomin.github.io/skill/design/image/skill/iconSkill_0134.png",
      "difficulty": 3,
      "prerequisites": "サンクチュアリ[6] 回顧[6]",
      "description": "聖霊を宿し、敵にかけられた各種補助魔法を解除する。",
      "powerup": "成功確率, CP減少量",
      "magicAttr": null,
      "hasPhysDmgPct": false,
      "hasMagicDmgRange": false,
      "hasAttackCount": false,
      "hasActivationRate": false,
      "levelKeys": [
        1,
        2,
        3,
        4,
        5,
        6,
        7,
        8,
        9,
        10,
        20,
        30,
        40,
        50
      ],
      "levels": {
        "1": {
          "consumeCp": 16,
          "gainCp": 0,
          "range": "7m"
        },
        "2": {
          "consumeCp": 17,
          "gainCp": 0,
          "range": "7m"
        },
        "3": {
          "consumeCp": 18,
          "gainCp": 0,
          "range": "7m"
        },
        "4": {
          "consumeCp": 19,
          "gainCp": 0,
          "range": "7m"
        },
        "5": {
          "consumeCp": 20,
          "gainCp": 0,
          "range": "7m"
        },
        "6": {
          "consumeCp": 21,
          "gainCp": 0,
          "range": "7m"
        },
        "7": {
          "consumeCp": 22,
          "gainCp": 0,
          "range": "7m"
        },
        "8": {
          "consumeCp": 23,
          "gainCp": 0,
          "range": "7m"
        },
        "9": {
          "consumeCp": 24,
          "gainCp": 0,
          "range": "7m"
        },
        "10": {
          "consumeCp": 25,
          "gainCp": 0,
          "range": "7m"
        },
        "20": {
          "consumeCp": 35,
          "gainCp": 0,
          "range": "7m"
        },
        "30": {
          "consumeCp": 45,
          "gainCp": 0,
          "range": "7m"
        },
        "40": {
          "consumeCp": 55,
          "gainCp": 0,
          "range": "7m"
        },
        "50": {
          "consumeCp": 65,
          "gainCp": 0,
          "range": "7m"
        }
      }
    },
    {
      "id": 135,
      "name": "エバンジェリズム",
      "icon": "https://sokomin.github.io/skill/design/image/skill/iconSkill_0135.png",
      "difficulty": 3,
      "prerequisites": "マジックディスペリング[3] ホーリーサークル[3] 想起[3]",
      "description": "敵を教化して味方にすると同時に、敵の信仰心を吸収し、自身の能力を強化する。",
      "powerup": "成功確率, 限界レベル",
      "magicAttr": null,
      "hasPhysDmgPct": false,
      "hasMagicDmgRange": false,
      "hasAttackCount": false,
      "hasActivationRate": false,
      "levelKeys": [
        1,
        2,
        3,
        4,
        5,
        6,
        7,
        8,
        9,
        10,
        20,
        30,
        40,
        50
      ],
      "levels": {
        "1": {
          "consumeCp": 32,
          "gainCp": 0
        },
        "2": {
          "consumeCp": 34,
          "gainCp": 0
        },
        "3": {
          "consumeCp": 36,
          "gainCp": 0
        },
        "4": {
          "consumeCp": 38,
          "gainCp": 0
        },
        "5": {
          "consumeCp": 40,
          "gainCp": 0
        },
        "6": {
          "consumeCp": 42,
          "gainCp": 0
        },
        "7": {
          "consumeCp": 44,
          "gainCp": 0
        },
        "8": {
          "consumeCp": 46,
          "gainCp": 0
        },
        "9": {
          "consumeCp": 48,
          "gainCp": 0
        },
        "10": {
          "consumeCp": 50,
          "gainCp": 0
        },
        "20": {
          "consumeCp": 70,
          "gainCp": 0
        },
        "30": {
          "consumeCp": 90,
          "gainCp": 0
        },
        "40": {
          "consumeCp": 110,
          "gainCp": 0
        },
        "50": {
          "consumeCp": 130,
          "gainCp": 0
        }
      }
    },
    {
      "id": 136,
      "name": "サンクチュアリ",
      "icon": "https://sokomin.github.io/skill/design/image/skill/iconSkill_0136.png",
      "difficulty": 2,
      "prerequisites": "ヒーリング[3] 回想[6]",
      "description": "しばらく敵の全ての攻撃から自分を保護してくれる絶対的な防御膜を形成する。 持続時間中は歩きを除いた一切のスキルアクションは不可能となる。",
      "powerup": "",
      "magicAttr": null,
      "hasPhysDmgPct": false,
      "hasMagicDmgRange": false,
      "hasAttackCount": false,
      "hasActivationRate": false,
      "levelKeys": [
        1,
        2,
        3,
        4,
        5,
        6,
        7,
        8,
        9,
        10,
        20,
        30,
        40,
        50
      ],
      "levels": {
        "1": {
          "consumeCp": 16,
          "gainCp": 0
        },
        "2": {
          "consumeCp": 17,
          "gainCp": 0
        },
        "3": {
          "consumeCp": 18,
          "gainCp": 0
        },
        "4": {
          "consumeCp": 19,
          "gainCp": 0
        },
        "5": {
          "consumeCp": 20,
          "gainCp": 0
        },
        "6": {
          "consumeCp": 21,
          "gainCp": 0
        },
        "7": {
          "consumeCp": 22,
          "gainCp": 0
        },
        "8": {
          "consumeCp": 23,
          "gainCp": 0
        },
        "9": {
          "consumeCp": 24,
          "gainCp": 0
        },
        "10": {
          "consumeCp": 25,
          "gainCp": 0
        },
        "20": {
          "consumeCp": 35,
          "gainCp": 0
        },
        "30": {
          "consumeCp": 45,
          "gainCp": 0
        },
        "40": {
          "consumeCp": 55,
          "gainCp": 0
        },
        "50": {
          "consumeCp": 65,
          "gainCp": 0
        }
      }
    },
    {
      "id": 137,
      "name": "エバキュエイション",
      "icon": "https://sokomin.github.io/skill/design/image/skill/iconSkill_0137.png",
      "difficulty": 3,
      "prerequisites": "サンクチュアリ[6]",
      "description": "自分を近くの安全な町に移動する。",
      "powerup": "キャスティング速度, 成功確率",
      "magicAttr": null,
      "hasPhysDmgPct": false,
      "hasMagicDmgRange": false,
      "hasAttackCount": false,
      "hasActivationRate": false,
      "levelKeys": [
        1,
        2,
        3,
        4,
        5,
        6,
        7,
        8,
        9,
        10,
        20,
        30,
        40,
        50
      ],
      "levels": {
        "1": {
          "consumeCp": 150.5,
          "gainCp": 3.5
        },
        "2": {
          "consumeCp": 151,
          "gainCp": 7
        },
        "3": {
          "consumeCp": 151.5,
          "gainCp": 10.5
        },
        "4": {
          "consumeCp": 152,
          "gainCp": 14
        },
        "5": {
          "consumeCp": 152.5,
          "gainCp": 17.5
        },
        "6": {
          "consumeCp": 153,
          "gainCp": 21
        },
        "7": {
          "consumeCp": 153.5,
          "gainCp": 24.5
        },
        "8": {
          "consumeCp": 154,
          "gainCp": 28
        },
        "9": {
          "consumeCp": 154.5,
          "gainCp": 31.5
        },
        "10": {
          "consumeCp": 155,
          "gainCp": 35
        },
        "20": {
          "consumeCp": 160,
          "gainCp": 70
        },
        "30": {
          "consumeCp": 165,
          "gainCp": 105
        },
        "40": {
          "consumeCp": 170,
          "gainCp": 140
        },
        "50": {
          "consumeCp": 175,
          "gainCp": 175
        }
      }
    },
    {
      "id": 138,
      "name": "コーリング",
      "icon": "https://sokomin.github.io/skill/design/image/skill/iconSkill_0138.png",
      "difficulty": 4,
      "prerequisites": "サンクチュアリ[12] エバキュエイション[6] 想起[3]",
      "description": "パーティーメンバーを自分の周囲に呼び寄せる。 追放天使のパーティーメンバーは瞬く間に術者の周囲にテレポートされる。 呼び出したパーティーメンバーを麻痺させてしまう事と、不安定な大気によって失敗してしまう事があるのが短所。",
      "powerup": "移動距離",
      "magicAttr": null,
      "hasPhysDmgPct": false,
      "hasMagicDmgRange": false,
      "hasAttackCount": false,
      "hasActivationRate": false,
      "levelKeys": [
        1,
        2,
        3,
        4,
        5,
        6,
        7,
        8,
        9,
        10,
        20,
        30,
        40,
        50
      ],
      "levels": {
        "1": {
          "consumeCp": 301.5,
          "gainCp": 7
        },
        "2": {
          "consumeCp": 303,
          "gainCp": 14
        },
        "3": {
          "consumeCp": 304.5,
          "gainCp": 21
        },
        "4": {
          "consumeCp": 306,
          "gainCp": 28
        },
        "5": {
          "consumeCp": 307.5,
          "gainCp": 35
        },
        "6": {
          "consumeCp": 309,
          "gainCp": 42
        },
        "7": {
          "consumeCp": 310.5,
          "gainCp": 49
        },
        "8": {
          "consumeCp": 312,
          "gainCp": 56
        },
        "9": {
          "consumeCp": 313.5,
          "gainCp": 63
        },
        "10": {
          "consumeCp": 315,
          "gainCp": 70
        },
        "20": {
          "consumeCp": 330,
          "gainCp": 140
        },
        "30": {
          "consumeCp": 345,
          "gainCp": 210
        },
        "40": {
          "consumeCp": 360,
          "gainCp": 280
        },
        "50": {
          "consumeCp": 375,
          "gainCp": 350
        }
      }
    },
    {
      "id": 139,
      "name": "タウンポータル",
      "icon": "https://sokomin.github.io/skill/design/image/skill/iconSkill_0139.png",
      "difficulty": 5,
      "prerequisites": "エバキュエイション[12] コーリング[6] 郷愁[3]",
      "description": "近くの安全な町へと通じるポータルを開く。 このポータルは一方通行で、持続時間内であれば他のプレイヤーたちも使用できる。",
      "powerup": "持続時間, 移動距離",
      "magicAttr": null,
      "hasPhysDmgPct": false,
      "hasMagicDmgRange": false,
      "hasAttackCount": false,
      "hasActivationRate": false,
      "levelKeys": [
        1,
        2,
        3,
        4,
        5,
        6,
        7,
        8,
        9,
        10,
        20,
        30,
        40,
        50
      ],
      "levels": {
        "1": {
          "consumeCp": 503,
          "gainCp": 12
        },
        "2": {
          "consumeCp": 506,
          "gainCp": 24
        },
        "3": {
          "consumeCp": 509,
          "gainCp": 36
        },
        "4": {
          "consumeCp": 512,
          "gainCp": 48
        },
        "5": {
          "consumeCp": 515,
          "gainCp": 60
        },
        "6": {
          "consumeCp": 518,
          "gainCp": 72
        },
        "7": {
          "consumeCp": 521,
          "gainCp": 84
        },
        "8": {
          "consumeCp": 524,
          "gainCp": 96
        },
        "9": {
          "consumeCp": 527,
          "gainCp": 108
        },
        "10": {
          "consumeCp": 530,
          "gainCp": 120
        },
        "20": {
          "consumeCp": 560,
          "gainCp": 240
        },
        "30": {
          "consumeCp": 590,
          "gainCp": 360
        },
        "40": {
          "consumeCp": 620,
          "gainCp": 480
        },
        "50": {
          "consumeCp": 650,
          "gainCp": 600
        }
      }
    },
    {
      "id": 140,
      "name": "ディテクティングエビル",
      "icon": "https://sokomin.github.io/skill/design/image/skill/iconSkill_0140.png",
      "difficulty": 1,
      "prerequisites": "なし",
      "description": "周辺にいる敵の邪悪な気を探知する。 画面内にいながら見えない敵と、画面外の一定距離にいる敵を探知する。",
      "powerup": "範囲",
      "magicAttr": null,
      "hasPhysDmgPct": false,
      "hasMagicDmgRange": false,
      "hasAttackCount": false,
      "hasActivationRate": false,
      "levelKeys": [
        1,
        2,
        3,
        4,
        5,
        6,
        7,
        8,
        9,
        10,
        20,
        30,
        40,
        50
      ],
      "levels": {
        "1": {
          "gainCp": 0.1
        },
        "2": {
          "gainCp": 0.2
        },
        "3": {
          "gainCp": 0.3
        },
        "4": {
          "gainCp": 0.4
        },
        "5": {
          "gainCp": 0.5
        },
        "6": {
          "gainCp": 0.6
        },
        "7": {
          "gainCp": 0.7
        },
        "8": {
          "gainCp": 0.8
        },
        "9": {
          "gainCp": 0.9
        },
        "10": {
          "gainCp": 1
        },
        "20": {
          "gainCp": 2
        },
        "30": {
          "gainCp": 3
        },
        "40": {
          "gainCp": 4
        },
        "50": {
          "gainCp": 5
        }
      }
    },
    {
      "id": 141,
      "name": "デストロイングアンデッド",
      "icon": "https://sokomin.github.io/skill/design/image/skill/iconSkill_0141.png",
      "difficulty": 2,
      "prerequisites": "ディクティングエビル[6] 回想[6]",
      "description": "自分の周囲一定半径内にいる敵を神聖な力で制圧する。 相対的に弱い一部アンデッドたちは逃げ出すか麻痺を受け、また一部の邪悪な敵は光の力でダメージを受ける。 また、相手を麻痺状態にする。",
      "powerup": "範囲, 限界レベル",
      "magicAttr": "light",
      "hasPhysDmgPct": false,
      "hasMagicDmgRange": true,
      "hasAttackCount": false,
      "hasActivationRate": false,
      "levelKeys": [
        1,
        2,
        3,
        4,
        5,
        6,
        7,
        8,
        9,
        10,
        20,
        30,
        40,
        50
      ],
      "levels": {
        "1": {
          "consumeCp": 15.5,
          "gainCp": 0.2,
          "attackRange": "3.5m",
          "magicDmgMin": 1,
          "magicDmgMax": 2
        },
        "2": {
          "consumeCp": 16,
          "gainCp": 0.4,
          "attackRange": "3.5m",
          "magicDmgMin": 1,
          "magicDmgMax": 4
        },
        "3": {
          "consumeCp": 16.5,
          "gainCp": 0.6,
          "attackRange": "3.5m",
          "magicDmgMin": 1,
          "magicDmgMax": 5
        },
        "4": {
          "consumeCp": 17,
          "gainCp": 0.8,
          "attackRange": "3.5m",
          "magicDmgMin": 1,
          "magicDmgMax": 7
        },
        "5": {
          "consumeCp": 17.5,
          "gainCp": 1,
          "attackRange": "3.5m",
          "magicDmgMin": 1,
          "magicDmgMax": 8
        },
        "6": {
          "consumeCp": 18,
          "gainCp": 1.2,
          "attackRange": "3.5m",
          "magicDmgMin": 1,
          "magicDmgMax": 9
        },
        "7": {
          "consumeCp": 18.5,
          "gainCp": 1.4,
          "attackRange": "3.5m",
          "magicDmgMin": 1,
          "magicDmgMax": 11
        },
        "8": {
          "consumeCp": 19,
          "gainCp": 1.6,
          "attackRange": "3.5m",
          "magicDmgMin": 1,
          "magicDmgMax": 12
        },
        "9": {
          "consumeCp": 19.5,
          "gainCp": 1.8,
          "attackRange": "3.5m",
          "magicDmgMin": 1,
          "magicDmgMax": 14
        },
        "10": {
          "consumeCp": 20,
          "gainCp": 2,
          "attackRange": "3.5m",
          "magicDmgMin": 1,
          "magicDmgMax": 15
        },
        "20": {
          "consumeCp": 25,
          "gainCp": 4,
          "attackRange": "3.5m",
          "magicDmgMin": 1,
          "magicDmgMax": 29
        },
        "30": {
          "consumeCp": 30,
          "gainCp": 6,
          "attackRange": "3.5m",
          "magicDmgMin": 1,
          "magicDmgMax": 43
        },
        "40": {
          "consumeCp": 35,
          "gainCp": 8,
          "attackRange": "3.5m",
          "magicDmgMin": 1,
          "magicDmgMax": 57
        },
        "50": {
          "consumeCp": 40,
          "gainCp": 10,
          "attackRange": "3.5m",
          "magicDmgMin": 1,
          "magicDmgMax": 71
        }
      }
    },
    {
      "id": 142,
      "name": "デストロイングアンホーリー",
      "icon": "https://sokomin.github.io/skill/design/image/skill/iconSkill_0142.png",
      "difficulty": 3,
      "prerequisites": "デストロイングアンデッド[6] 回顧[6]",
      "description": "自分の周囲一定半径内のアンデッド、悪魔系の敵を神聖な力で屈服させる。 聖なる光により敵の光属性抵抗力が低下する。",
      "powerup": "範囲、光抵抗減少",
      "magicAttr": null,
      "hasPhysDmgPct": false,
      "hasMagicDmgRange": false,
      "hasAttackCount": false,
      "hasActivationRate": false,
      "levelKeys": [
        1,
        2,
        3,
        4,
        5,
        6,
        7,
        8,
        9,
        10,
        20,
        30,
        40,
        50
      ],
      "levels": {
        "1": {
          "consumeCp": 54,
          "gainCp": 0
        },
        "2": {
          "consumeCp": 58,
          "gainCp": 0
        },
        "3": {
          "consumeCp": 62,
          "gainCp": 0
        },
        "4": {
          "consumeCp": 66,
          "gainCp": 0
        },
        "5": {
          "consumeCp": 70,
          "gainCp": 0
        },
        "6": {
          "consumeCp": 74,
          "gainCp": 0
        },
        "7": {
          "consumeCp": 78,
          "gainCp": 0
        },
        "8": {
          "consumeCp": 82,
          "gainCp": 0
        },
        "9": {
          "consumeCp": 86,
          "gainCp": 0
        },
        "10": {
          "consumeCp": 90,
          "gainCp": 0
        },
        "20": {
          "consumeCp": 130,
          "gainCp": 0
        },
        "30": {
          "consumeCp": 170,
          "gainCp": 0
        },
        "40": {
          "consumeCp": 210,
          "gainCp": 0
        },
        "50": {
          "consumeCp": 250,
          "gainCp": 0
        }
      }
    },
    {
      "id": 143,
      "name": "サンクンライトニング",
      "icon": "https://sokomin.github.io/skill/design/image/skill/iconSkill_0143.png",
      "difficulty": 4,
      "prerequisites": "デストロイングアンホーリー[6] ヘブンリープレシング[12]",
      "description": "追放天使が物理攻撃を繰り出す際に、天空から召喚された複数の稲妻が敵に落ちる。",
      "powerup": "威力",
      "magicAttr": "light",
      "hasPhysDmgPct": false,
      "hasMagicDmgRange": true,
      "hasAttackCount": false,
      "hasActivationRate": false,
      "levelKeys": [
        1,
        2,
        3,
        4,
        5,
        6,
        7,
        8,
        9,
        10,
        20,
        30,
        40,
        50
      ],
      "levels": {
        "1": {
          "magicDmgMin": 1,
          "magicDmgMax": 9
        },
        "2": {
          "magicDmgMin": 1,
          "magicDmgMax": 17
        },
        "3": {
          "magicDmgMin": 1,
          "magicDmgMax": 25
        },
        "4": {
          "magicDmgMin": 1,
          "magicDmgMax": 33
        },
        "5": {
          "magicDmgMin": 1,
          "magicDmgMax": 41
        },
        "6": {
          "magicDmgMin": 1,
          "magicDmgMax": 49
        },
        "7": {
          "magicDmgMin": 1,
          "magicDmgMax": 57
        },
        "8": {
          "magicDmgMin": 1,
          "magicDmgMax": 65
        },
        "9": {
          "magicDmgMin": 1,
          "magicDmgMax": 73
        },
        "10": {
          "magicDmgMin": 1,
          "magicDmgMax": 81
        },
        "20": {
          "magicDmgMin": 1,
          "magicDmgMax": 161
        },
        "30": {
          "magicDmgMin": 1,
          "magicDmgMax": 241
        },
        "40": {
          "magicDmgMin": 1,
          "magicDmgMax": 321
        },
        "50": {
          "magicDmgMin": 1,
          "magicDmgMax": 401
        }
      }
    },
    {
      "id": 144,
      "name": "ホーリークロス",
      "icon": "https://sokomin.github.io/skill/design/image/skill/iconSkill_0144.png",
      "difficulty": 5,
      "prerequisites": "ヒーリング[18] サンクチュアリ[18] デストロイングアンホーリー[12] 郷愁[6]",
      "description": "巨大な光の十字架を召喚して、指定した周囲にいる一定半径内の敵を攻撃。 その力でパーティーメンバーの体力を回復する。 知識値によって回復量が増加する。",
      "powerup": "威力、回復量、範囲",
      "magicAttr": "light",
      "hasPhysDmgPct": false,
      "hasMagicDmgRange": true,
      "hasAttackCount": false,
      "hasActivationRate": false,
      "levelKeys": [
        1,
        2,
        3,
        4,
        5,
        6,
        7,
        8,
        9,
        10,
        20,
        30,
        40,
        50
      ],
      "levels": {
        "1": {
          "consumeCp": 154,
          "gainCp": 0,
          "magicDmgMin": 1,
          "magicDmgMax": 13,
          "attackRange": "2.03m"
        },
        "2": {
          "consumeCp": 158,
          "gainCp": 0,
          "magicDmgMin": 1,
          "magicDmgMax": 25,
          "attackRange": "2.06m"
        },
        "3": {
          "consumeCp": 162,
          "gainCp": 0,
          "magicDmgMin": 1,
          "magicDmgMax": 37,
          "attackRange": "2.09m"
        },
        "4": {
          "consumeCp": 166,
          "gainCp": 0,
          "magicDmgMin": 1,
          "magicDmgMax": 49,
          "attackRange": "2.12m"
        },
        "5": {
          "consumeCp": 170,
          "gainCp": 0,
          "magicDmgMin": 1,
          "magicDmgMax": 61,
          "attackRange": "2.15m"
        },
        "6": {
          "consumeCp": 174,
          "gainCp": 0,
          "magicDmgMin": 1,
          "magicDmgMax": 73,
          "attackRange": "2.18m"
        },
        "7": {
          "consumeCp": 178,
          "gainCp": 0,
          "magicDmgMin": 1,
          "magicDmgMax": 85,
          "attackRange": "2.21m"
        },
        "8": {
          "consumeCp": 182,
          "gainCp": 0,
          "magicDmgMin": 1,
          "magicDmgMax": 97,
          "attackRange": "2.24m"
        },
        "9": {
          "consumeCp": 186,
          "gainCp": 0,
          "magicDmgMin": 1,
          "magicDmgMax": 109,
          "attackRange": "2.27m"
        },
        "10": {
          "consumeCp": 190,
          "gainCp": 0,
          "magicDmgMin": 1,
          "magicDmgMax": 121,
          "attackRange": "2.3m"
        },
        "20": {
          "consumeCp": 230,
          "gainCp": 0,
          "magicDmgMin": 1,
          "magicDmgMax": 241,
          "attackRange": "2.6m"
        },
        "30": {
          "consumeCp": 270,
          "gainCp": 0,
          "magicDmgMin": 1,
          "magicDmgMax": 361,
          "attackRange": "2.9m"
        },
        "40": {
          "consumeCp": 310,
          "gainCp": 0,
          "magicDmgMin": 1,
          "magicDmgMax": 481,
          "attackRange": "3.2m"
        },
        "50": {
          "consumeCp": 350,
          "gainCp": 0,
          "magicDmgMin": 1,
          "magicDmgMax": 601,
          "attackRange": "3.5m"
        }
      }
    },
    {
      "id": 145,
      "name": "ジャッジメントデイ",
      "icon": "https://sokomin.github.io/skill/design/image/skill/iconSkill_0145.png",
      "difficulty": 5,
      "prerequisites": "ホールドパーソン[24] ホールドモンスター[18] サンクンライトニング[6] 想起[12]",
      "description": "無数の十字架で一定範囲内の敵を攻撃する。",
      "powerup": "威力, 範囲",
      "magicAttr": "light",
      "hasPhysDmgPct": false,
      "hasMagicDmgRange": true,
      "hasAttackCount": false,
      "hasActivationRate": false,
      "levelKeys": [
        1,
        2,
        3,
        4,
        5,
        6,
        7,
        8,
        9,
        10,
        20,
        30,
        40,
        50
      ],
      "levels": {
        "1": {
          "consumeCp": 106,
          "gainCp": 0,
          "magicDmgMin": 1,
          "magicDmgMax": 15,
          "attackRange": "2.52m"
        },
        "2": {
          "consumeCp": 112,
          "gainCp": 0,
          "magicDmgMin": 1,
          "magicDmgMax": 29,
          "attackRange": "2.54m"
        },
        "3": {
          "consumeCp": 118,
          "gainCp": 0,
          "magicDmgMin": 1,
          "magicDmgMax": 43,
          "attackRange": "2.56m"
        },
        "4": {
          "consumeCp": 124,
          "gainCp": 0,
          "magicDmgMin": 1,
          "magicDmgMax": 57,
          "attackRange": "2.58m"
        },
        "5": {
          "consumeCp": 130,
          "gainCp": 0,
          "magicDmgMin": 1,
          "magicDmgMax": 71,
          "attackRange": "2.6m"
        },
        "6": {
          "consumeCp": 136,
          "gainCp": 0,
          "magicDmgMin": 1,
          "magicDmgMax": 85,
          "attackRange": "2.62m"
        },
        "7": {
          "consumeCp": 142,
          "gainCp": 0,
          "magicDmgMin": 1,
          "magicDmgMax": 99,
          "attackRange": "2.64m"
        },
        "8": {
          "consumeCp": 148,
          "gainCp": 0,
          "magicDmgMin": 1,
          "magicDmgMax": 113,
          "attackRange": "2.66m"
        },
        "9": {
          "consumeCp": 154,
          "gainCp": 0,
          "magicDmgMin": 1,
          "magicDmgMax": 127,
          "attackRange": "2.68m"
        },
        "10": {
          "consumeCp": 160,
          "gainCp": 0,
          "magicDmgMin": 1,
          "magicDmgMax": 141,
          "attackRange": "2.7m"
        },
        "20": {
          "consumeCp": 220,
          "gainCp": 0,
          "magicDmgMin": 1,
          "magicDmgMax": 281,
          "attackRange": "2.9m"
        },
        "30": {
          "consumeCp": 280,
          "gainCp": 0,
          "magicDmgMin": 1,
          "magicDmgMax": 421,
          "attackRange": "3.1m"
        },
        "40": {
          "consumeCp": 340,
          "gainCp": 0,
          "magicDmgMin": 1,
          "magicDmgMax": 561,
          "attackRange": "3.3m"
        },
        "50": {
          "consumeCp": 400,
          "gainCp": 0,
          "magicDmgMin": 1,
          "magicDmgMax": 701,
          "attackRange": "3.5m"
        }
      }
    },
    {
      "id": 146,
      "name": "回想",
      "icon": "https://sokomin.github.io/skill/design/image/skill/iconSkill_0146.png",
      "difficulty": 1,
      "prerequisites": "異端審問[3]",
      "description": "昔の自分が使った天上の魔法を回想して潜在能力を呼び出す。 上級技術を使うための準備行動をとる。",
      "powerup": "キャスティング速度",
      "magicAttr": null,
      "hasPhysDmgPct": false,
      "hasMagicDmgRange": false,
      "hasAttackCount": false,
      "hasActivationRate": false,
      "levelKeys": [
        1,
        2,
        3,
        4,
        5,
        6,
        7,
        8,
        9,
        10,
        20,
        30,
        40,
        50
      ],
      "levels": {
        "1": {
          "consumeCp": 0,
          "gainCp": 10.6
        },
        "2": {
          "consumeCp": 0,
          "gainCp": 11.2
        },
        "3": {
          "consumeCp": 0,
          "gainCp": 11.8
        },
        "4": {
          "consumeCp": 0,
          "gainCp": 12.4
        },
        "5": {
          "consumeCp": 0,
          "gainCp": 13
        },
        "6": {
          "consumeCp": 0,
          "gainCp": 13.6
        },
        "7": {
          "consumeCp": 0,
          "gainCp": 14.2
        },
        "8": {
          "consumeCp": 0,
          "gainCp": 14.8
        },
        "9": {
          "consumeCp": 0,
          "gainCp": 15.4
        },
        "10": {
          "consumeCp": 0,
          "gainCp": 16
        },
        "20": {
          "consumeCp": 0,
          "gainCp": 22
        },
        "30": {
          "consumeCp": 0,
          "gainCp": 28
        },
        "40": {
          "consumeCp": 0,
          "gainCp": 34
        },
        "50": {
          "consumeCp": 0,
          "gainCp": 40
        }
      }
    },
    {
      "id": 147,
      "name": "回顧",
      "icon": "https://sokomin.github.io/skill/design/image/skill/iconSkill_0147.png",
      "difficulty": 2,
      "prerequisites": "祈祷[3]",
      "description": "過ぎ去りし時を回顧し、以前の能力を引き出せるように集中する。 周囲にいるパーティーメンバーの全体速度が上昇する。",
      "powerup": "キャスティング速度、速度増加率、持続時間",
      "magicAttr": null,
      "hasPhysDmgPct": false,
      "hasMagicDmgRange": false,
      "hasAttackCount": false,
      "hasActivationRate": false,
      "levelKeys": [
        1,
        2,
        3,
        4,
        5,
        6,
        7,
        8,
        9,
        10,
        20,
        30,
        40,
        50
      ],
      "levels": {
        "1": {
          "consumeCp": 15,
          "gainCp": 31.2,
          "attackSpeed": 5.25
        },
        "2": {
          "consumeCp": 15,
          "gainCp": 32.4,
          "attackSpeed": 5.5
        },
        "3": {
          "consumeCp": 15,
          "gainCp": 33.6,
          "attackSpeed": 5.75
        },
        "4": {
          "consumeCp": 15,
          "gainCp": 34.8,
          "attackSpeed": 6
        },
        "5": {
          "consumeCp": 15,
          "gainCp": 36,
          "attackSpeed": 6.25
        },
        "6": {
          "consumeCp": 15,
          "gainCp": 37.2,
          "attackSpeed": 6.5
        },
        "7": {
          "consumeCp": 15,
          "gainCp": 38.4,
          "attackSpeed": 6.75
        },
        "8": {
          "consumeCp": 15,
          "gainCp": 39.6,
          "attackSpeed": 7
        },
        "9": {
          "consumeCp": 15,
          "gainCp": 40.8,
          "attackSpeed": 7.25
        },
        "10": {
          "consumeCp": 15,
          "gainCp": 42,
          "attackSpeed": 7.5
        },
        "20": {
          "consumeCp": 15,
          "gainCp": 54,
          "attackSpeed": 10
        },
        "30": {
          "consumeCp": 15,
          "gainCp": 66,
          "attackSpeed": 12.5
        },
        "40": {
          "consumeCp": 15,
          "gainCp": 78,
          "attackSpeed": 15
        },
        "50": {
          "consumeCp": 15,
          "gainCp": 90,
          "attackSpeed": 17.5
        }
      }
    },
    {
      "id": 148,
      "name": "想起",
      "icon": "https://sokomin.github.io/skill/design/image/skill/iconSkill_0148.png",
      "difficulty": 3,
      "prerequisites": "聖霊盾術[3]",
      "description": "過去を想起することで、天使であった頃の能力を発揮する。 追放天使の物理ダメージが上昇する。",
      "powerup": "物理ダメージ増加",
      "magicAttr": null,
      "hasPhysDmgPct": false,
      "hasMagicDmgRange": false,
      "hasAttackCount": false,
      "hasActivationRate": false,
      "levelKeys": [
        1,
        2,
        3,
        4,
        5,
        6,
        7,
        8,
        9,
        10,
        20,
        30,
        40,
        50
      ],
      "levels": {
        "1": {},
        "2": {},
        "3": {},
        "4": {},
        "5": {},
        "6": {},
        "7": {},
        "8": {},
        "9": {},
        "10": {},
        "20": {},
        "30": {},
        "40": {},
        "50": {}
      }
    },
    {
      "id": 149,
      "name": "郷愁",
      "icon": "https://sokomin.github.io/skill/design/image/skill/iconSkill_0149.png",
      "difficulty": 4,
      "prerequisites": "賛美[3]",
      "description": "天使であった頃の郷愁の念が一定時間天使の能力を付与してくれる。 天上の祝福スキルを保有している場合は、一定時間自身の周囲のパーティーメンバーの物理、魔法ダメージが上昇する。",
      "powerup": "キャスティング速度、物理、魔法ダメージ増加",
      "magicAttr": null,
      "hasPhysDmgPct": false,
      "hasMagicDmgRange": false,
      "hasAttackCount": false,
      "hasActivationRate": false,
      "levelKeys": [
        1,
        2,
        3,
        4,
        5,
        6,
        7,
        8,
        9,
        10,
        20,
        30,
        40,
        50
      ],
      "levels": {
        "1": {
          "consumeCp": 60,
          "gainCp": 107
        },
        "2": {
          "consumeCp": 60,
          "gainCp": 114
        },
        "3": {
          "consumeCp": 60,
          "gainCp": 121
        },
        "4": {
          "consumeCp": 60,
          "gainCp": 128
        },
        "5": {
          "consumeCp": 60,
          "gainCp": 135
        },
        "6": {
          "consumeCp": 60,
          "gainCp": 142
        },
        "7": {
          "consumeCp": 60,
          "gainCp": 149
        },
        "8": {
          "consumeCp": 60,
          "gainCp": 156
        },
        "9": {
          "consumeCp": 60,
          "gainCp": 163
        },
        "10": {
          "consumeCp": 60,
          "gainCp": 170
        },
        "20": {
          "consumeCp": 60,
          "gainCp": 240
        },
        "30": {
          "consumeCp": 60,
          "gainCp": 310
        },
        "40": {
          "consumeCp": 60,
          "gainCp": 380
        },
        "50": {
          "consumeCp": 60,
          "gainCp": 450
        }
      }
    }
  ]
}