{
  "job": {
    "id": "archer_awake",
    "jobId": 2,
    "label": "アーチャー 覚醒",
    "source": "archer_awake_skill20210224.html",
    "awake": true
  },
  "skills": [
    {
      "id": 1876,
      "name": "[専用覚醒] インターバルボマー",
      "icon": "https://sokomin.github.io/skill/design/image/skill/iconSkill_0220.png",
      "difficulty": 3,
      "prerequisites": "インターバルシューター[50]",
      "description": "矢を使うスキルを使用すると追加で打撃を与える魔法の弓を生成する。 魔法の弓はより長く使用でき、自動でアーチャーの矢の攻撃と同時に攻撃する。",
      "powerup": "威力、持続時間",
      "magicAttr": null,
      "hasPhysDmgPct": true,
      "hasMagicDmgRange": false,
      "hasAttackCount": true,
      "hasActivationRate": false,
      "levelKeys": [
        0,
        1,
        2,
        3,
        4,
        5,
        50
      ],
      "levels": {
        "0": {
          "consumeCp": 105,
          "gainCp": 100,
          "physDmgPct": 50,
          "attackCount": "5回"
        },
        "1": {
          "consumeCp": 106.5,
          "gainCp": 102,
          "physDmgPct": 51,
          "attackCount": "5回"
        },
        "2": {
          "consumeCp": 108,
          "gainCp": 104,
          "physDmgPct": 52,
          "attackCount": "5回"
        },
        "3": {
          "consumeCp": 109.5,
          "gainCp": 106,
          "physDmgPct": 53,
          "attackCount": "5回"
        },
        "4": {
          "consumeCp": 111,
          "gainCp": 108,
          "physDmgPct": 54,
          "attackCount": "5回"
        },
        "5": {
          "consumeCp": 112.5,
          "gainCp": 110,
          "physDmgPct": 55,
          "attackCount": "5回"
        },
        "50": {
          "consumeCp": "...",
          "gainCp": "...",
          "physDmgPct": "...",
          "attackCount": "5回"
        }
      }
    },
    {
      "id": 1877,
      "name": "シャドウチェイサー",
      "icon": "https://sokomin.github.io/skill/design/image/skill/iconSkill_0209.png",
      "difficulty": 5,
      "prerequisites": "テイルチェイサー[50]",
      "description": "他のアーチャー技術で敵を攻撃する時にそれが命中すると、数発の矢が自動発射され、追加でさらに多数の矢を発射する。",
      "powerup": "威力",
      "magicAttr": null,
      "hasPhysDmgPct": true,
      "hasMagicDmgRange": false,
      "hasAttackCount": true,
      "hasActivationRate": true,
      "levelKeys": [
        0,
        1,
        2,
        3,
        4,
        5,
        50
      ],
      "levels": {
        "0": {
          "consumeCp": 50,
          "gainCp": 0,
          "physDmgPct": "85％",
          "accuracy": 100,
          "activationRatePct": 95,
          "attackCount": "6回"
        },
        "1": {
          "consumeCp": 51,
          "gainCp": 0,
          "physDmgPct": "85％",
          "accuracy": 100,
          "activationRatePct": 96,
          "attackCount": "6回"
        },
        "2": {
          "consumeCp": 52,
          "gainCp": 0,
          "physDmgPct": "85％",
          "accuracy": 100,
          "activationRatePct": 97,
          "attackCount": "6回"
        },
        "3": {
          "consumeCp": 53,
          "gainCp": 0,
          "physDmgPct": "85％",
          "accuracy": 100,
          "activationRatePct": 98,
          "attackCount": "6回"
        },
        "4": {
          "consumeCp": 54,
          "gainCp": 0,
          "physDmgPct": "85％",
          "accuracy": 100,
          "activationRatePct": 99,
          "attackCount": "6回"
        },
        "5": {
          "consumeCp": 55,
          "gainCp": 0,
          "physDmgPct": "85％",
          "accuracy": 100,
          "activationRatePct": 100,
          "attackCount": "6回"
        },
        "50": {
          "consumeCp": "...",
          "gainCp": 0,
          "physDmgPct": "85％",
          "accuracy": 100,
          "activationRatePct": "...",
          "attackCount": "6回"
        }
      }
    },
    {
      "id": 1878,
      "name": "バラージショット",
      "icon": "https://sokomin.github.io/skill/design/image/skill/iconSkill_0216.png",
      "difficulty": 2,
      "prerequisites": "マシーンアロー[50]",
      "description": "複数の矢を一体の敵に向かって連射し、発射速度が増加する。",
      "powerup": "威力",
      "magicAttr": null,
      "hasPhysDmgPct": true,
      "hasMagicDmgRange": false,
      "hasAttackCount": true,
      "hasActivationRate": false,
      "levelKeys": [
        0,
        1,
        2,
        3,
        4,
        5,
        50
      ],
      "levels": {
        "0": {
          "consumeCp": 120,
          "gainCp": 60,
          "physDmgPct": 100,
          "accuracy": 100,
          "attackCount": "12回"
        },
        "1": {
          "consumeCp": 122,
          "gainCp": 61,
          "physDmgPct": 102,
          "accuracy": 100,
          "attackCount": "12回"
        },
        "2": {
          "consumeCp": 124,
          "gainCp": 62,
          "physDmgPct": 104,
          "accuracy": 100,
          "attackCount": "12回"
        },
        "3": {
          "consumeCp": 126,
          "gainCp": 63,
          "physDmgPct": 106,
          "accuracy": 100,
          "attackCount": "12回"
        },
        "4": {
          "consumeCp": 128,
          "gainCp": 64,
          "physDmgPct": 108,
          "accuracy": 100,
          "attackCount": "12回"
        },
        "5": {
          "consumeCp": 130,
          "gainCp": 65,
          "physDmgPct": 110,
          "accuracy": 100,
          "attackCount": "12回"
        },
        "50": {
          "consumeCp": "...",
          "gainCp": "...",
          "physDmgPct": "...",
          "accuracy": 100,
          "attackCount": "12回"
        }
      }
    },
    {
      "id": 1879,
      "name": "[専用覚醒] リワインドマーカー",
      "icon": "https://sokomin.github.io/skill/design/image/skill/iconSkill_0219.png",
      "difficulty": 4,
      "prerequisites": "ランドマーカー[50]",
      "description": "魔力を込めた爆弾の矢を発射する。 爆弾は周辺の敵に粘着され爆発し、5回粘着されると自動で爆発して大きなダメージを与える。 爆発後敵が退治できなかった場合、爆弾が再粘着される。 再粘着された爆弾はリワインドマーカーの影響を受け再び爆発する。",
      "powerup": "威力、打撃範囲",
      "magicAttr": "fire",
      "hasPhysDmgPct": false,
      "hasMagicDmgRange": true,
      "hasAttackCount": false,
      "hasActivationRate": false,
      "levelKeys": [
        0,
        1,
        2,
        3,
        4,
        5,
        50
      ],
      "levels": {
        "0": {
          "consumeCp": 260,
          "gainCp": 0,
          "magicDmgMin": 56,
          "magicDmgMax": 57,
          "attackRange": "2.5m"
        },
        "1": {
          "consumeCp": 264,
          "gainCp": 0,
          "magicDmgMin": 57,
          "magicDmgMax": 58,
          "attackRange": "2.53m"
        },
        "2": {
          "consumeCp": 268,
          "gainCp": 0,
          "magicDmgMin": 58,
          "magicDmgMax": 59,
          "attackRange": "2.56m"
        },
        "3": {
          "consumeCp": 272,
          "gainCp": 0,
          "magicDmgMin": 59,
          "magicDmgMax": 60,
          "attackRange": "2.59m"
        },
        "4": {
          "consumeCp": 276,
          "gainCp": 0,
          "magicDmgMin": 60,
          "magicDmgMax": 61,
          "attackRange": "2.62m"
        },
        "5": {
          "consumeCp": 280,
          "gainCp": 0,
          "magicDmgMin": 61,
          "magicDmgMax": 62,
          "attackRange": "2.65m"
        },
        "50": {
          "consumeCp": "...",
          "gainCp": 0,
          "attackRange": "..."
        }
      }
    },
    {
      "id": 1880,
      "name": "イリュージョンアーチャー",
      "icon": "https://sokomin.github.io/skill/design/image/skill/iconSkill_0814.png",
      "difficulty": 2,
      "prerequisites": "マジカルアロー[50]",
      "description": "アーチャーと共にいる蜃気楼を召喚する。 蜃気楼はアーチャーの属性ダメージスキルをコピーして攻撃する。",
      "powerup": "威力",
      "magicAttr": null,
      "hasPhysDmgPct": false,
      "hasMagicDmgRange": false,
      "hasAttackCount": false,
      "hasActivationRate": false,
      "levelKeys": [
        0,
        1,
        2,
        3,
        4,
        5,
        50
      ],
      "levels": {
        "0": {
          "consumeCp": 0,
          "gainCp": 50
        },
        "1": {
          "consumeCp": 0,
          "gainCp": 51
        },
        "2": {
          "consumeCp": 0,
          "gainCp": 52
        },
        "3": {
          "consumeCp": 0,
          "gainCp": 53
        },
        "4": {
          "consumeCp": 0,
          "gainCp": 54
        },
        "5": {
          "consumeCp": 0,
          "gainCp": 55
        },
        "50": {
          "consumeCp": 0,
          "gainCp": "..."
        }
      }
    },
    {
      "id": 1881,
      "name": "ハーモニックアロー",
      "icon": "https://sokomin.github.io/skill/design/image/skill/iconSkill_0809.png",
      "difficulty": 2,
      "prerequisites": "デュアルアロー[50]",
      "description": "魔法で火と氷の魔力を込めた矢を生成し連射する。",
      "powerup": "威力",
      "magicAttr": "fire",
      "hasPhysDmgPct": false,
      "hasMagicDmgRange": true,
      "hasAttackCount": true,
      "hasActivationRate": false,
      "levelKeys": [
        0,
        1,
        2,
        3,
        4,
        5,
        50
      ],
      "levels": {
        "0": {
          "consumeCp": 65,
          "gainCp": 50,
          "magicDmgMin": 53,
          "magicDmgMax": 55,
          "attackCount": "12回(マシーンアロー方式)"
        },
        "1": {
          "consumeCp": 66,
          "gainCp": 51,
          "magicDmgMin": 54,
          "magicDmgMax": 56,
          "attackCount": "12回(マシーンアロー方式)"
        },
        "2": {
          "consumeCp": 67,
          "gainCp": 52,
          "magicDmgMin": 55,
          "magicDmgMax": 57,
          "attackCount": "12回(マシーンアロー方式)"
        },
        "3": {
          "consumeCp": 68,
          "gainCp": 53,
          "magicDmgMin": 56,
          "magicDmgMax": 58,
          "attackCount": "12回(マシーンアロー方式)"
        },
        "4": {
          "consumeCp": 69,
          "gainCp": 54,
          "magicDmgMin": 57,
          "magicDmgMax": 59,
          "attackCount": "12回(マシーンアロー方式)"
        },
        "5": {
          "consumeCp": 70,
          "gainCp": 55,
          "magicDmgMin": 58,
          "magicDmgMax": 60,
          "attackCount": "12回(マシーンアロー方式)"
        },
        "50": {
          "consumeCp": "...",
          "gainCp": "...",
          "attackCount": "12回(マシーンアロー方式)"
        }
      }
    },
    {
      "id": 1882,
      "name": "[専用覚醒] レイヤーテンペスト",
      "icon": "https://sokomin.github.io/skill/design/image/skill/iconSkill_0217.png",
      "difficulty": 3,
      "prerequisites": "レイヤーストーム[50]",
      "description": "超近接用矢のスキルで周りの敵を攻撃する。 遠距離にいる敵に使用すると、打撃範囲がなくなる。 近距離にいるさらに多数の敵を攻撃可能になる。",
      "powerup": "威力",
      "magicAttr": null,
      "hasPhysDmgPct": true,
      "hasMagicDmgRange": false,
      "hasAttackCount": false,
      "hasActivationRate": false,
      "levelKeys": [
        0,
        1,
        2,
        3,
        4,
        5,
        50
      ],
      "levels": {
        "0": {
          "consumeCp": 140,
          "gainCp": 50,
          "physDmgPct": 200,
          "attackRange": "3m"
        },
        "1": {
          "consumeCp": 142,
          "gainCp": 51,
          "physDmgPct": 204,
          "attackRange": "3m"
        },
        "2": {
          "consumeCp": 144,
          "gainCp": 52,
          "physDmgPct": 208,
          "attackRange": "3m"
        },
        "3": {
          "consumeCp": 146,
          "gainCp": 53,
          "physDmgPct": 212,
          "attackRange": "3m"
        },
        "4": {
          "consumeCp": 148,
          "gainCp": 54,
          "physDmgPct": 216,
          "attackRange": "3m"
        },
        "5": {
          "consumeCp": 150,
          "gainCp": 55,
          "physDmgPct": 220,
          "attackRange": "3m"
        },
        "50": {
          "consumeCp": "...",
          "gainCp": "...",
          "physDmgPct": "...",
          "attackRange": "3m"
        }
      }
    },
    {
      "id": 1883,
      "name": "バーストショット",
      "icon": "https://sokomin.github.io/skill/design/image/skill/iconSkill_0202.png",
      "difficulty": 2,
      "prerequisites": "ピアシングアロー[50]",
      "description": "矢で敵を貫通して攻撃し、出血状態にする。 出血状態の敵を攻撃すると、出血ダメージをもう一回与える事ができる。",
      "powerup": "威力",
      "magicAttr": null,
      "hasPhysDmgPct": true,
      "hasMagicDmgRange": false,
      "hasAttackCount": false,
      "hasActivationRate": false,
      "levelKeys": [
        0,
        1,
        2,
        3,
        4,
        5,
        50
      ],
      "levels": {
        "0": {
          "consumeCp": 40,
          "gainCp": 65,
          "physDmgPct": 150
        },
        "1": {
          "consumeCp": 40.5,
          "gainCp": 66.3,
          "physDmgPct": 153
        },
        "2": {
          "consumeCp": 41,
          "gainCp": 67.6,
          "physDmgPct": 156
        },
        "3": {
          "consumeCp": 41.5,
          "gainCp": 68.9,
          "physDmgPct": 159
        },
        "4": {
          "consumeCp": 42,
          "gainCp": 70.2,
          "physDmgPct": 162
        },
        "5": {
          "consumeCp": 42.5,
          "gainCp": 71.5,
          "physDmgPct": 165
        },
        "50": {
          "consumeCp": "...",
          "gainCp": "...",
          "physDmgPct": "..."
        }
      }
    },
    {
      "id": 1884,
      "name": "シーカーミサイル",
      "icon": "https://sokomin.github.io/skill/design/image/skill/iconSkill_0212.png",
      "difficulty": 2,
      "prerequisites": "シーカーアロー[50]",
      "description": "敵を追いかける誘導矢を発射する。 敵にロックオンした矢は敵に当たったり、死んだりするまで追いかける。 敵を退治できなかった場合、アーチャーが敵の前に移動する。",
      "powerup": "威力",
      "magicAttr": null,
      "hasPhysDmgPct": true,
      "hasMagicDmgRange": false,
      "hasAttackCount": false,
      "hasActivationRate": false,
      "levelKeys": [
        0,
        1,
        2,
        3,
        4,
        5,
        50
      ],
      "levels": {
        "0": {
          "consumeCp": 40,
          "gainCp": 40,
          "physDmgPct": 110,
          "accuracy": 100
        },
        "1": {
          "consumeCp": 40.5,
          "gainCp": 40.8,
          "physDmgPct": 112,
          "accuracy": 100
        },
        "2": {
          "consumeCp": 41,
          "gainCp": 41.6,
          "physDmgPct": 114,
          "accuracy": 100
        },
        "3": {
          "consumeCp": 41.5,
          "gainCp": 42.4,
          "physDmgPct": 116,
          "accuracy": 100
        },
        "4": {
          "consumeCp": 42,
          "gainCp": 43.2,
          "physDmgPct": 118,
          "accuracy": 100
        },
        "5": {
          "consumeCp": 42.5,
          "gainCp": 44,
          "physDmgPct": 120,
          "accuracy": 100
        },
        "50": {
          "consumeCp": "...",
          "gainCp": "...",
          "physDmgPct": "...",
          "accuracy": 100
        }
      }
    }
  ]
}