{"_sig":"(c) sokomin - created by sokomin (https://sokomin.github.io)","0x0028":"<br><a name=\"0x0028\"></a><table id=\"table1\"><colgroup><col span=\"1\" width=\"40\"><col span=\"1\" width=\"180\"><col span=\"1\" width=\"180\"><col span=\"1\"><col span=\"1\"></colgroup><tbody><tr><th colspan=\"5\" valign=\"top\"><font color=\"#e8c898\"><font color=\"#ffffff\">力の水薬</font></font></th></tr><tr><td rowspan=\"2\"><img src=\"../item/design/image/item/iconItem_0039.png\"></td><td colspan=\"4\" valign=\"top\"><font color=\"#00f8f8\">&lt;基本情報&gt;</font><br>- ステータスポーション<br>- 力 +[<font color=\"#f8f800\">5</font>~<font color=\"#f8f800\">100</font>] [<font color=\"#f8f800\">60</font>~<font color=\"#f8f800\">180</font>]秒<br></td></tr><tr><td valign=\"top\"><font color=\"#00f8f8\">&lt;要求能力値&gt;</font><br>- 力 5 ~ 100<br></td><td valign=\"top\"><font color=\"#00f8f8\">&lt;着用可能な職業&gt;</font><br></td><td valign=\"top\"><font color=\"#00f8f8\">&lt;DropLv/係数&gt;</font><br>60/1000</td><td valign=\"top\"><font color=\"#00f8f8\">&lt;価格&gt;</font><br>[補正値] * <font color=\"#f8f800\">3</font> Gold<br></td></tr><tr><td colspan=\"5\"><font color=\"#00f8f8\">&lt;説明&gt;</font><br>- でこぼこの透明な瓶に入っている赤い水薬<br><br>- <font color=\"#ff0033\">ベルト着用可</font></td></tr></tbody></table>","0x0029":"<br><a name=\"0x0029\"></a><table id=\"table1\"><colgroup><col span=\"1\" width=\"40\"><col span=\"1\" width=\"180\"><col span=\"1\" width=\"180\"><col span=\"1\"><col span=\"1\"></colgroup><tbody><tr><th colspan=\"5\" valign=\"top\"><font color=\"#e8c898\"><font color=\"#ffffff\">素早さの水薬</font></font></th></tr><tr><td rowspan=\"2\"><img src=\"../item/design/image/item/iconItem_0040.png\"></td><td colspan=\"4\" valign=\"top\"><font color=\"#00f8f8\">&lt;基本情報&gt;</font><br>- ステータスポーション<br>- 敏捷 +[<font color=\"#f8f800\">5</font>~<font color=\"#f8f800\">100</font>] [<font color=\"#f8f800\">60</font>~<font color=\"#f8f800\">180</font>]秒<br></td></tr><tr><td valign=\"top\"><font color=\"#00f8f8\">&lt;要求能力値&gt;</font><br>- 敏捷 5 ~ 100<br></td><td valign=\"top\"><font color=\"#00f8f8\">&lt;着用可能な職業&gt;</font><br></td><td valign=\"top\"><font color=\"#00f8f8\">&lt;DropLv/係数&gt;</font><br>60/1000</td><td valign=\"top\"><font color=\"#00f8f8\">&lt;価格&gt;</font><br>[補正値] * <font color=\"#f8f800\">3</font> Gold<br></td></tr><tr><td colspan=\"5\"><font color=\"#00f8f8\">&lt;説明&gt;</font><br>- 滑らかで薄い瓶に入っている緑色の水薬<br><br>- <font color=\"#ff0033\">ベルト着用可</font></td></tr></tbody></table>","0x002a":"<br><a name=\"0x002a\"></a><table id=\"table1\"><colgroup><col span=\"1\" width=\"40\"><col span=\"1\" width=\"180\"><col span=\"1\" width=\"180\"><col span=\"1\"><col span=\"1\"></colgroup><tbody><tr><th colspan=\"5\" valign=\"top\"><font color=\"#e8c898\"><font color=\"#ffffff\">元気の水薬</font></font></th></tr><tr><td rowspan=\"2\"><img src=\"../item/design/image/item/iconItem_0041.png\"></td><td colspan=\"4\" valign=\"top\"><font color=\"#00f8f8\">&lt;基本情報&gt;</font><br>- ステータスポーション<br>- 健康 +[<font color=\"#f8f800\">5</font>~<font color=\"#f8f800\">100</font>] [<font color=\"#f8f800\">60</font>~<font color=\"#f8f800\">180</font>]秒<br></td></tr><tr><td valign=\"top\"><font color=\"#00f8f8\">&lt;要求能力値&gt;</font><br>- 健康 5 ~ 100<br></td><td valign=\"top\"><font color=\"#00f8f8\">&lt;着用可能な職業&gt;</font><br></td><td valign=\"top\"><font color=\"#00f8f8\">&lt;DropLv/係数&gt;</font><br>60/1000</td><td valign=\"top\"><font color=\"#00f8f8\">&lt;価格&gt;</font><br>[補正値] * <font color=\"#f8f800\">3</font> Gold<br></td></tr><tr><td colspan=\"5\"><font color=\"#00f8f8\">&lt;説明&gt;</font><br>- ぽっちゃりした透明な瓶に入っている黄色い水薬<br><br>- <font color=\"#ff0033\">ベルト着用可</font></td></tr></tbody></table>","0x002b":"<br><a name=\"0x002b\"></a><table id=\"table1\"><colgroup><col span=\"1\" width=\"40\"><col span=\"1\" width=\"180\"><col span=\"1\" width=\"180\"><col span=\"1\"><col span=\"1\"></colgroup><tbody><tr><th colspan=\"5\" valign=\"top\"><font color=\"#e8c898\"><font color=\"#ffffff\">知恵の書</font></font></th></tr><tr><td rowspan=\"2\"><img src=\"../item/design/image/item/iconItem_0042.png\"></td><td colspan=\"4\" valign=\"top\"><font color=\"#00f8f8\">&lt;基本情報&gt;</font><br>- ステータスポーション<br>- 知恵 +[<font color=\"#f8f800\">5</font>~<font color=\"#f8f800\">100</font>] [<font color=\"#f8f800\">60</font>~<font color=\"#f8f800\">180</font>]秒<br></td></tr><tr><td valign=\"top\"><font color=\"#00f8f8\">&lt;要求能力値&gt;</font><br>- 知恵 5 ~ 100<br></td><td valign=\"top\"><font color=\"#00f8f8\">&lt;着用可能な職業&gt;</font><br></td><td valign=\"top\"><font color=\"#00f8f8\">&lt;DropLv/係数&gt;</font><br>60/1000</td><td valign=\"top\"><font color=\"#00f8f8\">&lt;価格&gt;</font><br>[補正値] * <font color=\"#f8f800\">3</font> Gold<br></td></tr><tr><td colspan=\"5\"><font color=\"#00f8f8\">&lt;説明&gt;</font><br>- 青い表紙の本<br><br>- <font color=\"#ff0033\">ベルト着用可</font></td></tr></tbody></table>","0x002c":"<br><a name=\"0x002c\"></a><table id=\"table1\"><colgroup><col span=\"1\" width=\"40\"><col span=\"1\" width=\"180\"><col span=\"1\" width=\"180\"><col span=\"1\"><col span=\"1\"></colgroup><tbody><tr><th colspan=\"5\" valign=\"top\"><font color=\"#e8c898\"><font color=\"#ffffff\">知識の巻物</font></font></th></tr><tr><td rowspan=\"2\"><img src=\"../item/design/image/item/iconItem_0043.png\"></td><td colspan=\"4\" valign=\"top\"><font color=\"#00f8f8\">&lt;基本情報&gt;</font><br>- ステータスポーション<br>- 知識 +[<font color=\"#f8f800\">5</font>~<font color=\"#f8f800\">100</font>] [<font color=\"#f8f800\">60</font>~<font color=\"#f8f800\">180</font>]秒<br></td></tr><tr><td valign=\"top\"><font color=\"#00f8f8\">&lt;要求能力値&gt;</font><br>- 知識 5 ~ 100<br></td><td valign=\"top\"><font color=\"#00f8f8\">&lt;着用可能な職業&gt;</font><br></td><td valign=\"top\"><font color=\"#00f8f8\">&lt;DropLv/係数&gt;</font><br>60/1000</td><td valign=\"top\"><font color=\"#00f8f8\">&lt;価格&gt;</font><br>[補正値] * <font color=\"#f8f800\">3</font> Gold<br></td></tr><tr><td colspan=\"5\"><font color=\"#00f8f8\">&lt;説明&gt;</font><br>- 白い巻物<br><br>- <font color=\"#ff0033\">ベルト着用可</font></td></tr></tbody></table>","0x002d":"<br><a name=\"0x002d\"></a><table id=\"table1\"><colgroup><col span=\"1\" width=\"40\"><col span=\"1\" width=\"180\"><col span=\"1\" width=\"180\"><col span=\"1\"><col span=\"1\"></colgroup><tbody><tr><th colspan=\"5\" valign=\"top\"><font color=\"#e8c898\"><font color=\"#ffffff\">カリスマの護身符</font></font></th></tr><tr><td rowspan=\"2\"><img src=\"../item/design/image/item/iconItem_0044.png\"></td><td colspan=\"4\" valign=\"top\"><font color=\"#00f8f8\">&lt;基本情報&gt;</font><br>- ステータスポーション<br>- カリスマ +[<font color=\"#f8f800\">5</font>~<font color=\"#f8f800\">100</font>] [<font color=\"#f8f800\">60</font>~<font color=\"#f8f800\">180</font>]秒<br></td></tr><tr><td valign=\"top\"><font color=\"#00f8f8\">&lt;要求能力値&gt;</font><br>- カリスマ 5 ~ 100<br></td><td valign=\"top\"><font color=\"#00f8f8\">&lt;着用可能な職業&gt;</font><br></td><td valign=\"top\"><font color=\"#00f8f8\">&lt;DropLv/係数&gt;</font><br>60/1000</td><td valign=\"top\"><font color=\"#00f8f8\">&lt;価格&gt;</font><br>[補正値] * <font color=\"#f8f800\">3</font> Gold<br></td></tr><tr><td colspan=\"5\"><font color=\"#00f8f8\">&lt;説明&gt;</font><br>- 黒くて複雑な形の､金属で出来たお守り<br><br>- <font color=\"#ff0033\">ベルト着用可</font></td></tr></tbody></table>","0x002e":"<br><a name=\"0x002e\"></a><table id=\"table1\"><colgroup><col span=\"1\" width=\"40\"><col span=\"1\" width=\"180\"><col span=\"1\" width=\"180\"><col span=\"1\"><col span=\"1\"></colgroup><tbody><tr><th colspan=\"5\" valign=\"top\"><font color=\"#e8c898\"><font color=\"#ffffff\">幸運のクローバ</font></font></th></tr><tr><td rowspan=\"2\"><img src=\"../item/design/image/item/iconItem_0045.png\"></td><td colspan=\"4\" valign=\"top\"><font color=\"#00f8f8\">&lt;基本情報&gt;</font><br>- ステータスポーション<br>- 運を [<font color=\"#f8f800\">5</font>~<font color=\"#f8f800\">100</font>]だけ [<font color=\"#f8f800\">60</font>~<font color=\"#f8f800\">180</font>]秒間上昇させる。<br></td></tr><tr><td valign=\"top\"><font color=\"#00f8f8\">&lt;要求能力値&gt;</font><br>- 運 5 ~ 100<br></td><td valign=\"top\"><font color=\"#00f8f8\">&lt;着用可能な職業&gt;</font><br></td><td valign=\"top\"><font color=\"#00f8f8\">&lt;DropLv/係数&gt;</font><br>60/1000</td><td valign=\"top\"><font color=\"#00f8f8\">&lt;価格&gt;</font><br>[補正値] * <font color=\"#f8f800\">3</font> Gold<br></td></tr><tr><td colspan=\"5\"><font color=\"#00f8f8\">&lt;説明&gt;</font><br>- 緑色の､四葉クローバ<br><br>- <font color=\"#ff0033\">ベルト着用可</font></td></tr></tbody></table>","0x032b":"<br><a name=\"0x032b\"></a><table id=\"table1\"><colgroup><col span=\"1\" width=\"40\"><col span=\"1\" width=\"180\"><col span=\"1\" width=\"180\"><col span=\"1\"><col span=\"1\"></colgroup><tbody><tr><th colspan=\"5\" valign=\"top\"><font color=\"#e8c898\"><font color=\"#ffffff\">サラマンダーの炎</font></font></th></tr><tr><td rowspan=\"2\"><img src=\"../item/design/image/item/iconItem_0277.png\"></td><td colspan=\"4\" valign=\"top\"><font color=\"#00f8f8\">&lt;基本情報&gt;</font><br>- ステータスポーション<br>- 火属性抵抗(％) +[<font color=\"#f8f800\">10</font>~<font color=\"#f8f800\">30</font>]％<br></td></tr><tr><td valign=\"top\"><font color=\"#00f8f8\">&lt;要求能力値&gt;</font><br>- 知恵 70 ~ 210<br></td><td valign=\"top\"><font color=\"#00f8f8\">&lt;着用可能な職業&gt;</font><br></td><td valign=\"top\"><font color=\"#00f8f8\">&lt;DropLv/係数&gt;</font><br>9999/1000</td><td valign=\"top\"><font color=\"#00f8f8\">&lt;価格&gt;</font><br><font color=\"#f8f800\">0</font> Gold<br></td></tr><tr><td colspan=\"5\"><font color=\"#00f8f8\">&lt;説明&gt;</font><br>- サラマンダーが消えた後に残った炎。いつ消えるかは解らないが、当分は使えると思う<br></td></tr></tbody></table>","0x032c":"<br><a name=\"0x032c\"></a><table id=\"table1\"><colgroup><col span=\"1\" width=\"40\"><col span=\"1\" width=\"180\"><col span=\"1\" width=\"180\"><col span=\"1\"><col span=\"1\"></colgroup><tbody><tr><th colspan=\"5\" valign=\"top\"><font color=\"#e8c898\"><font color=\"#ffffff\">青い水晶</font></font></th></tr><tr><td rowspan=\"2\"><img src=\"../item/design/image/item/iconItem_0085.png\"></td><td colspan=\"4\" valign=\"top\"><font color=\"#00f8f8\">&lt;基本情報&gt;</font><br>- ステータスポーション<br>- 水属性抵抗(％) +[<font color=\"#f8f800\">10</font>~<font color=\"#f8f800\">30</font>]％<br></td></tr><tr><td valign=\"top\"><font color=\"#00f8f8\">&lt;要求能力値&gt;</font><br>- 知恵 70 ~ 210<br></td><td valign=\"top\"><font color=\"#00f8f8\">&lt;着用可能な職業&gt;</font><br></td><td valign=\"top\"><font color=\"#00f8f8\">&lt;DropLv/係数&gt;</font><br>9999/1000</td><td valign=\"top\"><font color=\"#00f8f8\">&lt;価格&gt;</font><br><font color=\"#f8f800\">0</font> Gold<br></td></tr><tr><td colspan=\"5\"><font color=\"#00f8f8\">&lt;説明&gt;</font><br>- 水晶烏賊が消えた後に残った青い水晶。かすかに震えていていつ消えるかは解らないが、当分は使えると思う<br></td></tr></tbody></table>","0x032d":"<br><a name=\"0x032d\"></a><table id=\"table1\"><colgroup><col span=\"1\" width=\"40\"><col span=\"1\" width=\"180\"><col span=\"1\" width=\"180\"><col span=\"1\"><col span=\"1\"></colgroup><tbody><tr><th colspan=\"5\" valign=\"top\"><font color=\"#e8c898\"><font color=\"#ffffff\">大地のため息</font></font></th></tr><tr><td rowspan=\"2\"><img src=\"../item/design/image/item/iconItem_0079.png\"></td><td colspan=\"4\" valign=\"top\"><font color=\"#00f8f8\">&lt;基本情報&gt;</font><br>- ステータスポーション<br>- 大地属性抵抗(％) +[<font color=\"#f8f800\">10</font>~<font color=\"#f8f800\">30</font>]％<br></td></tr><tr><td valign=\"top\"><font color=\"#00f8f8\">&lt;要求能力値&gt;</font><br>- 知恵 70 ~ 210<br></td><td valign=\"top\"><font color=\"#00f8f8\">&lt;着用可能な職業&gt;</font><br></td><td valign=\"top\"><font color=\"#00f8f8\">&lt;DropLv/係数&gt;</font><br>9999/1000</td><td valign=\"top\"><font color=\"#00f8f8\">&lt;価格&gt;</font><br><font color=\"#f8f800\">0</font> Gold<br></td></tr><tr><td colspan=\"5\"><font color=\"#00f8f8\">&lt;説明&gt;</font><br>- ガーゴイルが消えた後に残った丸い石ころ。この石は息をしているような音を出し、少しづつ崩れているが、当分は使えると思う<br></td></tr></tbody></table>","0x032e":"<br><a name=\"0x032e\"></a><table id=\"table1\"><colgroup><col span=\"1\" width=\"40\"><col span=\"1\" width=\"180\"><col span=\"1\" width=\"180\"><col span=\"1\"><col span=\"1\"></colgroup><tbody><tr><th colspan=\"5\" valign=\"top\"><font color=\"#e8c898\"><font color=\"#ffffff\">風の種</font></font></th></tr><tr><td rowspan=\"2\"><img src=\"../item/design/image/item/iconItem_0013.png\"></td><td colspan=\"4\" valign=\"top\"><font color=\"#00f8f8\">&lt;基本情報&gt;</font><br>- ステータスポーション<br>- 風属性抵抗(％) +[<font color=\"#f8f800\">10</font>~<font color=\"#f8f800\">30</font>]％<br></td></tr><tr><td valign=\"top\"><font color=\"#00f8f8\">&lt;要求能力値&gt;</font><br>- 知恵 70 ~ 210<br></td><td valign=\"top\"><font color=\"#00f8f8\">&lt;着用可能な職業&gt;</font><br></td><td valign=\"top\"><font color=\"#00f8f8\">&lt;DropLv/係数&gt;</font><br>9999/1000</td><td valign=\"top\"><font color=\"#00f8f8\">&lt;価格&gt;</font><br><font color=\"#f8f800\">0</font> Gold<br></td></tr><tr><td colspan=\"5\"><font color=\"#00f8f8\">&lt;説明&gt;</font><br>- ケンタウロスが消えた後に残った、植物の種の様に見えるもの。これはかすかな風の音を出しながら震えている。いつ飛んで行ってしまうか解らないが、当分は使えると思う<br></td></tr></tbody></table>","0x032f":"<br><a name=\"0x032f\"></a><table id=\"table1\"><colgroup><col span=\"1\" width=\"40\"><col span=\"1\" width=\"180\"><col span=\"1\" width=\"180\"><col span=\"1\"><col span=\"1\"></colgroup><tbody><tr><th colspan=\"5\" valign=\"top\"><font color=\"#e8c898\"><font color=\"#ffffff\">闇の息吹</font></font></th></tr><tr><td rowspan=\"2\"><img src=\"../item/design/image/item/iconItem_0279.png\"></td><td colspan=\"4\" valign=\"top\"><font color=\"#00f8f8\">&lt;基本情報&gt;</font><br>- ステータスポーション<br>- 闇属性抵抗(％) +[<font color=\"#f8f800\">10</font>~<font color=\"#f8f800\">30</font>]％<br></td></tr><tr><td valign=\"top\"><font color=\"#00f8f8\">&lt;要求能力値&gt;</font><br>- 知恵 70 ~ 210<br></td><td valign=\"top\"><font color=\"#00f8f8\">&lt;着用可能な職業&gt;</font><br></td><td valign=\"top\"><font color=\"#00f8f8\">&lt;DropLv/係数&gt;</font><br>9999/1000</td><td valign=\"top\"><font color=\"#00f8f8\">&lt;価格&gt;</font><br><font color=\"#f8f800\">0</font> Gold<br></td></tr><tr><td colspan=\"5\"><font color=\"#00f8f8\">&lt;説明&gt;</font><br>- リプリートマーキが影の中へと消えた後に残った青い陽炎。この青い陽炎はいつ消えるかは解らないが、当分は使えると思う<br></td></tr></tbody></table>","0x033a":"<br><a name=\"0x033a\"></a><table id=\"table1\"><colgroup><col span=\"1\" width=\"40\"><col span=\"1\" width=\"180\"><col span=\"1\" width=\"180\"><col span=\"1\"><col span=\"1\"></colgroup><tbody><tr><th colspan=\"5\" valign=\"top\"><font color=\"#e8c898\"><font color=\"#ffffff\">かすかな閃光</font></font></th></tr><tr><td rowspan=\"2\"><img src=\"../item/design/image/item/iconItem_0031.png\"></td><td colspan=\"4\" valign=\"top\"><font color=\"#00f8f8\">&lt;基本情報&gt;</font><br>- ステータスポーション<br>- 光属性抵抗(％) +[<font color=\"#f8f800\">10</font>~<font color=\"#f8f800\">30</font>]％<br></td></tr><tr><td valign=\"top\"><font color=\"#00f8f8\">&lt;要求能力値&gt;</font><br>- 知恵 70 ~ 210<br></td><td valign=\"top\"><font color=\"#00f8f8\">&lt;着用可能な職業&gt;</font><br></td><td valign=\"top\"><font color=\"#00f8f8\">&lt;DropLv/係数&gt;</font><br>9999/1000</td><td valign=\"top\"><font color=\"#00f8f8\">&lt;価格&gt;</font><br><font color=\"#f8f800\">0</font> Gold<br></td></tr><tr><td colspan=\"5\"><font color=\"#00f8f8\">&lt;説明&gt;</font><br>- ウィルオウィスプが消えた後に現れた、かすかな光を発する鍵。この鍵は時々ぼやけて殆ど見えない時もあるが、消えるまでは使えそうだ<br></td></tr></tbody></table>","0x033b":"<br><a name=\"0x033b\"></a><table id=\"table1\"><colgroup><col span=\"1\" width=\"40\"><col span=\"1\" width=\"180\"><col span=\"1\" width=\"180\"><col span=\"1\"><col span=\"1\"></colgroup><tbody><tr><th colspan=\"5\" valign=\"top\"><font color=\"#e8c898\"><font color=\"#ffffff\">命の宝石</font></font></th></tr><tr><td rowspan=\"2\"><img src=\"../item/design/image/item/iconItem_0051.png\"></td><td colspan=\"4\" valign=\"top\"><font color=\"#00f8f8\">&lt;基本情報&gt;</font><br>- ステータスポーション<br>- 防御力 +[<font color=\"#f8f800\">10</font>~<font color=\"#f8f800\">30</font>]<br>- 物理致命打抵抗(％)増加 [<font color=\"#f8f800\">20</font>~<font color=\"#f8f800\">50</font>]％<br></td></tr><tr><td valign=\"top\"><font color=\"#00f8f8\">&lt;要求能力値&gt;</font><br>- 知恵 80 ~ 240<br></td><td valign=\"top\"><font color=\"#00f8f8\">&lt;着用可能な職業&gt;</font><br></td><td valign=\"top\"><font color=\"#00f8f8\">&lt;DropLv/係数&gt;</font><br>9999/1000</td><td valign=\"top\"><font color=\"#00f8f8\">&lt;価格&gt;</font><br><font color=\"#f8f800\">0</font> Gold<br></td></tr><tr><td colspan=\"5\"><font color=\"#00f8f8\">&lt;説明&gt;</font><br>- 生きた屍が倒れながら残した、心臓の様な形の宝石。この宝石は今にも立ち上がってどこかへ飛んで行きそうに見えるが、その前までは持っていれば役に立ちそうだ<br></td></tr></tbody></table>"}